bradford_white_wave_client/__init__.py
bradford_white_wave_client/auth.py
bradford_white_wave_client/client.py
bradford_white_wave_client/const.py
bradford_white_wave_client/exceptions.py
bradford_white_wave_client/models.py
bradford_white_wave_client-0.1.2.dist-info/METADATA
bradford_white_wave_client-0.1.2.dist-info/WHEEL
bradford_white_wave_client-0.1.2.dist-info/licenses/LICENSE
bradford_white_wave_client-0.1.2.dist-info/RECORD
