Metadata-Version: 2.4
Name: bradford_white_wave_client
Version: 0.1.2
Summary: Client for Bradford White Wave API
Project-URL: Homepage, https://github.com/gclenaghan/bradford-white-wave-client
Author-email: Graham Clenaghan <gclenaghan@gmail.com>
License-Expression: MIT
License-File: LICENSE
Classifier: Development Status :: 3 - Alpha
Classifier: Intended Audience :: Developers
Classifier: License :: OSI Approved :: MIT License
Classifier: Programming Language :: Python :: 3
Classifier: Programming Language :: Python :: 3.9
Classifier: Programming Language :: Python :: 3.10
Classifier: Programming Language :: Python :: 3.11
Classifier: Topic :: Home Automation
Classifier: Topic :: Software Development :: Libraries :: Python Modules
Requires-Python: >=3.9
Requires-Dist: aiohttp
Requires-Dist: pydantic
